colourtime-0.4.0.dist-info/WHEEL
colourtime-0.4.0.dist-info/RECORD
colourtime-0.4.0.dist-info/entry_points.txt
colourtime-0.4.0.dist-info/METADATA
colourtime/colourtime.cpython-38-x86_64-linux-gnu.so
colourtime/__init__.py
