Metadata-Version: 2.1
Name: colourtime
Version: 0.4.0
Classifier: Programming Language :: Python :: 3
Requires-Dist: event_stream
Requires-Dist: matplotlib
Requires-Dist: numpy
Requires-Dist: pillow
Summary: Represent time with colours
Author-email: Alexandre Marcireau <alexandre.marcireau@gmail.com>
License: MIT
